FACe_signer/FACe.py
FACe_signer/__init__.py
FACe_signer-0.1.5.dist-info/DESCRIPTION.rst
FACe_signer-0.1.5.dist-info/METADATA
FACe_signer-0.1.5.dist-info/RECORD
FACe_signer-0.1.5.dist-info/WHEEL
FACe_signer-0.1.5.dist-info/metadata.json
FACe_signer-0.1.5.dist-info/top_level.txt
