Metadata-Version: 2.0
Name: FACe-signer
Version: 0.1.5
Summary: Zeep plugin that signs FACe SOAP requests
Home-page: http://www.gisce.net
Author: GISCE-TI, S.L.
Author-email: devel@gisce.net
License: GNU GPLv3
Platform: UNKNOWN
Classifier: Programming Language :: Python
Classifier: Programming Language :: Python :: 2.7
Provides: FACe_signer
Requires-Dist: soap-wsse
Requires-Dist: zeep
Requires-Dist: pyOpenSSL (>16.1.0)
